{
  "assignee": "bewinxed@gmail.com",
  "claim_note": "",
  "claimed_at": "2026-01-20T06:26:12.097263Z",
  "created_at": "2026-01-20T06:10:29.982195Z",
  "depends_on": [
    "fn-1-c5m.2"
  ],
  "epic": "fn-1-c5m",
  "evidence": {
    "commits": [
      "ddfb91128ddc3271e7f5a86ad6cc84ff46aae34b"
    ],
    "prs": [],
    "tests": [
      "bun test src/state.test.ts",
      "./rp-cli --raw-json -e \"windows\""
    ]
  },
  "id": "fn-1-c5m.3",
  "priority": null,
  "spec_path": ".flow/tasks/fn-1-c5m.3.md",
  "status": "done",
  "title": "Windows command",
  "updated_at": "2026-01-20T08:22:21.785770Z"
}
